icpp_candid/__init__.py
icpp_candid/py.typed
icpp_candid/version.py
icpp_candid/candid/candid_args.cpp
icpp_candid/candid/candid_args.h
icpp_candid/candid/candid_assert.cpp
icpp_candid/candid/candid_assert.h
icpp_candid/candid/candid_constants.h
icpp_candid/candid/candid_debug_config.h
icpp_candid/candid/candid_deserialize.cpp
icpp_candid/candid/candid_deserialize.h
icpp_candid/candid/candid_opcode.cpp
icpp_candid/candid/candid_opcode.h
icpp_candid/candid/candid_serialize.cpp
icpp_candid/candid/candid_serialize.h
icpp_candid/candid/candid_serialize_type_table_registry.cpp
icpp_candid/candid/candid_serialize_type_table_registry.h
icpp_candid/candid/candid_type.h
icpp_candid/candid/candid_type_all_includes.h
icpp_candid/candid/candid_type_base.cpp
icpp_candid/candid/candid_type_base.h
icpp_candid/candid/candid_type_bool.cpp
icpp_candid/candid/candid_type_bool.h
icpp_candid/candid/candid_type_empty.cpp
icpp_candid/candid/candid_type_empty.h
icpp_candid/candid/candid_type_float32.cpp
icpp_candid/candid/candid_type_float32.h
icpp_candid/candid/candid_type_float64.cpp
icpp_candid/candid/candid_type_float64.h
icpp_candid/candid/candid_type_int.cpp
icpp_candid/candid/candid_type_int.h
icpp_candid/candid/candid_type_int16.cpp
icpp_candid/candid/candid_type_int16.h
icpp_candid/candid/candid_type_int32.cpp
icpp_candid/candid/candid_type_int32.h
icpp_candid/candid/candid_type_int64.cpp
icpp_candid/candid/candid_type_int64.h
icpp_candid/candid/candid_type_int8.cpp
icpp_candid/candid/candid_type_int8.h
icpp_candid/candid/candid_type_nat.cpp
icpp_candid/candid/candid_type_nat.h
icpp_candid/candid/candid_type_nat16.cpp
icpp_candid/candid/candid_type_nat16.h
icpp_candid/candid/candid_type_nat32.cpp
icpp_candid/candid/candid_type_nat32.h
icpp_candid/candid/candid_type_nat64.cpp
icpp_candid/candid/candid_type_nat64.h
icpp_candid/candid/candid_type_nat8.cpp
icpp_candid/candid/candid_type_nat8.h
icpp_candid/candid/candid_type_null.cpp
icpp_candid/candid/candid_type_null.h
icpp_candid-5.3.0.dist-info/licenses/LICENSE
icpp_candid-5.3.0.dist-info/METADATA
icpp_candid-5.3.0.dist-info/WHEEL
icpp_candid-5.3.0.dist-info/top_level.txt
icpp_candid-5.3.0.dist-info/RECORD
