Metadata-Version: 2.4
Name: icpp-candid
Version: 5.3.0
Summary: C++ Candid Library
Author-email: icpp-pro <icpp@icpp.world>
Maintainer-email: icpp-pro <icpp@icpp.world>
License: MIT License
Project-URL: Homepage, https://www.onicai.com/
Project-URL: Documentation, https://docs.icpp.world/
Project-URL: Repository, https://github.com/icppWorld/icpp-candid
Project-URL: Issues, https://github.com/icppWorld/icpp-candid/issues
Project-URL: Changelog, https://docs.icpp.world/release-notes.html#changelog
Keywords: C++ Candid Library,Internet Computer,C++,Candid,blockchain
Classifier: Development Status :: 4 - Beta
Classifier: License :: OSI Approved :: MIT License
Classifier: Programming Language :: Python :: 3
Classifier: Programming Language :: Python :: 3.9
Classifier: Programming Language :: Python :: 3.10
Classifier: Programming Language :: Python :: 3.11
Classifier: Programming Language :: Python :: 3.12
Classifier: Programming Language :: Python :: 3 :: Only
Requires-Python: >=3.9
License-File: LICENSE
Provides-Extra: dev
Requires-Dist: black==23.12.1; extra == "dev"
Requires-Dist: pylint==2.13.9; extra == "dev"
Requires-Dist: mypy==1.8.0; extra == "dev"
Requires-Dist: build==1.2.2; extra == "dev"
Requires-Dist: twine==6.0.1; extra == "dev"
Requires-Dist: mkdocs==1.5.3; extra == "dev"
Requires-Dist: types-requests==2.31.0.10; extra == "dev"
Dynamic: license-file
